{"datasets":[{"name":null,"slug":"u.s.-geological-society-seismic-design-seismic","kind":null,"group":"U.S. Geological Society Seismic Design","unit":null,"data":{"data":{"pgauh":0.217,"pgad":0.5,"pga":0.217,"fpga":1.383,"pgam":0.3,"ssrt":0.511,"crs":0.951,"ssuh":0.538,"ssd":1.5,"ss":0.511,"fa":1.391,"sms":0.711,"sds":0.474,"sdcs":"C","s1rt":0.22,"cr1":0.955,"s1uh":0.23,"s1d":0.6,"s1":0.22,"fv":null,"fv_note":"See Section 11.4.8","sm1":null,"sd1":null,"sdc1":null,"sdc":null,"tl":12,"t-sub-l":12,"cv":1.041,"twoPeriodDesignSpectrum":null,"twoPeriodMCErSpectrum":null,"verticalDesignSpectrum":[[null,null]],"verticalMCErSpectrum":[[null,null]]},"metadata":{"modelVersion":"v4.0.x","pgadFloor":0.5,"pgadPercentileFactor":1.8,"s1MaxDirFactor":1.3,"s1dFloor":0.6,"s1dPercentileFactor":1.8,"spatialInterpolationMethod":"linearloglinear","ssMaxDirFactor":1.1,"ssdFloor":1.5,"ssdPercentileFactor":1.8}}}],"elevation":253.2202383657837,"location":{"city":"Merced","county":"Merced County","state":"California"}}